{"cameraMode":{"drawMode":0,"name":"Shaded","section":"Shading Mode"},"sceneLighting":true,"audioPlay":false,"sceneViewState":{"showFog":true,"showMaterialUpdate":false,"showSkybox":true,"showFlares":true,"showImageEffects":true,"showParticleSystems":true},"in2DMode":false,"pivot":{"x":17.20318603515625,"y":4.88215970993042,"z":2.181654930114746},"rotation":{"x":-0.11717065423727036,"y":0.6582991480827332,"z":-0.10473476350307465,"w":-0.7361865043640137},"size":19.878644943237306,"orthographic":false}